termshape/__init__.py
termshape/termshape.py
termshape-1.2.0.dist-info/LICENSE
termshape-1.2.0.dist-info/METADATA
termshape-1.2.0.dist-info/WHEEL
termshape-1.2.0.dist-info/top_level.txt
termshape-1.2.0.dist-info/RECORD
