Metadata-Version: 2.1
Name: termshape
Version: 1.2.0
Summary: Tremshape is a minimalistic Python packgage, that only prints basic shapes on terminal.
Home-page: https://github.com/zvibazak/termshape
Download-URL: https://github.com/zvibazak/termshape/archive/v_0.0.2.tar.gz
Author: Zvi Bazak
Author-email: zvibazak@gmail.com
License: MIT
Keywords: terminal,shape
Classifier: Development Status :: 3 - Alpha
Classifier: Intended Audience :: Developers
Classifier: Topic :: Software Development :: Build Tools
Classifier: License :: OSI Approved :: MIT License
Classifier: Programming Language :: Python :: 3
Classifier: Programming Language :: Python :: 3.4
Classifier: Programming Language :: Python :: 3.5
Classifier: Programming Language :: Python :: 3.6
License-File: LICENSE
